<poster>How Murray Saved Christmas</poster>
<fanart>http://www.nbc.com/sites/nbcunbc/files/files/styles/nbc_show_about_cover/public/images/2014/11/03/2014_1031_HNSC_Aboutimage_1920x1080_KO.jpg?itok=ZuMG1P79</fanart>



<item>
<title>How Murray Saved Christmas (2014)</title>
<thumbnail>http://www.imdb.com/media/rm3878091008/tt3816346?ref_=tt_ov_i</thumbnail>
<link>
<sublink>http://v-vids.com/l7illhpc8rgz</sublink>
<sublink>http://vidbull.com/pngvatj53897.html</sublink>
<sublink>http://mightyupload.com/6wu5bf5rfytx/how.murray.saved.christmas.hdtv.x264-w4f.mp4.html</sublink>
<sublink>http://180upload.com/5w4u0e95xrqq</sublink>
<sublink></sublink>
<sublink></sublink>
<sublink></sublink>
</link>
</item>