<poster>The Christmas Spirit</poster>
<fanart>http://cdn2-b.examiner.com/sites/default/files/styles/image_content_width/hash/bf/79/bf792874b8a1243dc0ae3a07c37e4c5c.jpg?itok=yYxRgCHd</fanart>



<item>
<title>The Christmas Spirit (2013)</title>
<thumbnail>http://ia.media-imdb.com/images/M/MV5BMTU5NDIwNDMwNF5BMl5BanBnXkFtZTgwMTA0MDk2MDE@._V1_SX214_AL_.jpg</thumbnail>
<link>
<sublink>http://movreel.com/ehy0heghrz19.html</sublink>
<sublink>http://v-vids.com/fmcim7p9i2cl</sublink>
<sublink>http://vidbull.com/9myf6vn8r7m8.html</sublink>
<sublink>http://mightyupload.com/ifdzot5hs9vm/The.Christmas.Spirit.2013.Hallmark.Movie.HDTV.XviD.NoGRP.avi.html</sublink>
<sublink>http://180upload.com/rsuzmhpl3dvw</sublink>
<sublink></sublink>
<sublink></sublink>
</link>
</item>