<poster>Rambo</poster>
<fanart>https://raw.githubusercontent.com/foz1234/Anti-Matter/master/fanart.jpg</fanart>
<thumbnail>https://fanart.tv/detailpreview/fanart/movies/5039/movieposter/rambo-collection-53c14252092d2.jpg</thumbnail>

<message>(PRDL) PLEASE REPORT DEAD LINKS</message>
<thumbnail>https://pbs.twimg.com/profile_images/378800000859632875/-UddpgrN.png</thumbnail>
<message>[CR]</message>

<item>
<title>[B]Rambo : First Blood (1982)[/B]</title>
<thumbnail>http://image.tmdb.org/t/p/w396/v0sPtM5lGkLwtfDlWpn07nqJPyf.jpg</thumbnail>
<link>

<sublink>http://movreel.com/54igksrmwcsd</sublink>
<sublink>http://movreel.com/9wnulkbb7q9t</sublink>
</link>
</item>
 
<item>
<title>[B]Rambo: First Blood Part II (1985)[/B]</title>
<thumbnail>http://image.tmdb.org/t/p/w396/xYLmHi80zIlu3JDfJYfd1JY0Xl7.jpg</thumbnail>
<link>
<sublink>http://movreel.com/u4yrm8c0q9fu</sublink>
<sublink>http://movreel.com/4785p93agsia</sublink>
</link>
</item>

<item>
<title>[B]Rambo III (1988)[/B]</title>
<thumbnail>http://image.tmdb.org/t/p/w396/s54DchYWkSTCi9z7Is2IIX3qmvw.jpg</thumbnail>
<link>
<sublink>http://www.firedrive.com/file/LOXL5Q0FMPSWOCG</sublink>
<sublink>http://movreel.com/z5hyu76v0osl</sublink>
</link>
</item>

<item>
<title>[B]Rambo (2008)[/B]</title>
<thumbnail>http://image.tmdb.org/t/p/w396/nwCm80TFvA7pQAQdcGHs69ZeGOK.jpg</thumbnail>
<link>
<sublink>http://movreel.com/745oz64zy3md</sublink>
<sublink>http://movreel.com/745oz64zy3md</sublink>
</link>
</item>