<poster>Big Momma’s House</poster>
<fanart>http://images.digitalspy.co.uk/11/02/1200w_movies_big_mommas.jpg</fanart>

<info>
<message>[B][COLOR ffffff00] Big Momma’s House (2000) [/COLOR][/B]</message>
<thumbnail>http://blank</thumbnail>
<message>[B][COLOR ff00ff00] Genre: [/COLOR][/B] Action, Comedy, Crime </message>
<thumbnail>http://blank</thumbnail>
<message>[CR]</message>
<thumbnail>http://blank</thumbnail>
</info>



<item>
<title>Big Momma’s House</title>
<thumbnail>http://blank</thumbnail>
<link>
<sublink>http://movreel.com/k101acfkf00g.html</sublink>
<sublink>http://v-vids.com/eryqlgp169e9</sublink>
<sublink>http://vidbull.com/1an8rqwfajeh.html</sublink>
<sublink>http://mightyupload.com/clpw776rktun/Big.Momma's.House.2000.1080p.BluRay.x264.YIFY.mp4.html</sublink>
<sublink>http://hugefiles.net/07rsj3dh9bj3</sublink>
<sublink>http://180upload.com/0wr5ykwisnb2</sublink>
<sublink></sublink>
</link>
</item>

<info>
<message>[B][COLOR ffffff00]Plot:[/COLOR][/B] [B] An FBI agent disguises himself as an old lady to protect a beautiful federal witness and her son. [/B]</message>
<thumbnail>http://blank</thumbnail>
</info>