<poster>Houdini Part 2</poster>
<fanart>http://1.bp.blogspot.com/-TnO_NC4szgw/U73D0dlT36I/AAAAAAAAYeE/MJ_wi9z_3lk/s1600/Houdini-clip.jpg</fanart>



<item>
<title>Houdini Part 2 (2014) </title>
<thumbnail>http://www.imdb.com/media/rm2396176640/tt3132738?ref_=tt_ov_i</thumbnail>
<link>
<sublink>http://movreel.com/1mbwtyn6k31g.html</sublink>
<sublink>http://v-vids.com/c7x3z2n0t5cv</sublink>
<sublink>http://vidbull.com/z15wpip6g3yn.html</sublink>
<sublink>http://mightyupload.com/i4euyq1acc7d/Houdini.Part2.2014.EXTENDED.1080p.BluRay.x264.anoXmous.mp4.html</sublink>
<sublink>http://180upload.com/pfwhflw6y94g</sublink>
<sublink>http://mediafree.co/cacyrswf9yu5/Houdini.Part2.2014.EXTENDED.1080p.BluRay.x264.anoXmous.mp4.html</sublink>
<sublink></sublink>
</link>
</item>